README.md
setup.py
py_feslite.egg-info/PKG-INFO
py_feslite.egg-info/SOURCES.txt
py_feslite.egg-info/dependency_links.txt
py_feslite.egg-info/requires.txt
py_feslite.egg-info/top_level.txt
pyfeslite/__init__.py
pyfeslite/build_wrapper.py