Metadata-Version: 2.1
Name: py-feslite
Version: 0.0.2
Summary: A wrapper for libfes-lite
Home-page: https://github.com/cbouilla/pyfeslite
Author: Charles Bouillaguet
Author-email: charles.bouillaguet@univ-lille.fr
License: UNKNOWN
Platform: UNKNOWN
Classifier: Programming Language :: Python :: 3
Classifier: License :: OSI Approved :: GNU General Public License v3 (GPLv3)
Classifier: Operating System :: OS Independent
Classifier: Topic :: Scientific/Engineering :: Mathematics
Requires-Python: >=3.4
